[
  {
    "setCode": "POR",
    "nameFR": "",
    "nameEN": "Perfect Order",
    "releaseDate": "27-03-2026"
  },
  {
    "setCode": "ASC",
    "nameFR": "",
    "nameEN": "Ascended Heroes",
    "releaseDate": "30-01-2026"
  },
  {
    "setCode": "PFL",
    "nameFR": "",
    "nameEN": "Phantasmal Flames",
    "releaseDate": "14-11-2025"
  },
  {
    "setCode": "MEG",
    "nameFR": "",
    "nameEN": "Mega Evolution",
    "releaseDate": "26-09-2025"
  },
  {
    "setCode": "MEE",
    "nameFR": "",
    "nameEN": "Mega Evolution Energy",
    "releaseDate": "25-09-2025"
  },
  {
    "setCode": "MEP",
    "nameFR": "",
    "nameEN": "Mega Promos",
    "releaseDate": ""
  },
  {
    "setCode": "BLK",
    "nameFR": "",
    "nameEN": "Black Bolt",
    "releaseDate": "18-07-2025"
  },
  {
    "setCode": "WHT",
    "nameFR": "",
    "nameEN": "White Flare",
    "releaseDate": "18-07-2025"
  },
  {
    "setCode": "DRI",
    "nameFR": "",
    "nameEN": "Destined Rivals",
    "releaseDate": "30-05-2025"
  },
  {
    "setCode": "JTG",
    "nameFR": "",
    "nameEN": "Journey Together",
    "releaseDate": "28-03-2025"
  },
  {
    "setCode": "PRE",
    "nameFR": "",
    "nameEN": "Prismatic Evolutions",
    "releaseDate": "17-01-2025"
  },
  {
    "setCode": "SSP",
    "nameFR": "",
    "nameEN": "Surging Sparks",
    "releaseDate": "08-11-2024"
  },
  {
    "setCode": "SCR",
    "nameFR": "",
    "nameEN": "Stellar Crown",
    "releaseDate": "13-09-2024"
  },
  {
    "setCode": "SFA",
    "nameFR": "",
    "nameEN": "Shrouded Fable",
    "releaseDate": "02-08-2024"
  },
  {
    "setCode": "TWM",
    "nameFR": "",
    "nameEN": "Twilight Masquerade",
    "releaseDate": "24-05-2024"
  },
  {
    "setCode": "TEF",
    "nameFR": "",
    "nameEN": "Temporal Forces",
    "releaseDate": "22-03-2024"
  },
  {
    "setCode": "PAF",
    "nameFR": "",
    "nameEN": "Paldean Fates",
    "releaseDate": "26-01-2024"
  },
  {
    "setCode": "PAR",
    "nameFR": "",
    "nameEN": "Paradox Rift",
    "releaseDate": "03-11-2023"
  },
  {
    "setCode": "MEW",
    "nameFR": "",
    "nameEN": "Pokémon 151",
    "releaseDate": "22-09-2023"
  },
  {
    "setCode": "OBF",
    "nameFR": "",
    "nameEN": "Obsidian Flames",
    "releaseDate": "11-08-2023"
  },
  {
    "setCode": "PAL",
    "nameFR": "",
    "nameEN": "Paldea Evolved",
    "releaseDate": "09-06-2023"
  },
  {
    "setCode": "SVI",
    "nameFR": "",
    "nameEN": "Scarlet & Violet",
    "releaseDate": "31-03-2023"
  },
  {
    "setCode": "SVE",
    "nameFR": "",
    "nameEN": "Scarlet & Violet Energy",
    "releaseDate": "30-03-2023"
  },
  {
    "setCode": "SV-P",
    "nameFR": "",
    "nameEN": "Scarlet & Violet Promos",
    "releaseDate": ""
  },
  {
    "setCode": "CRZ",
    "nameFR": "",
    "nameEN": "Crown Zenith",
    "releaseDate": "20-01-2023"
  },
  {
    "setCode": "SIT",
    "nameFR": "",
    "nameEN": "Silver Tempest",
    "releaseDate": "11-11-2022"
  },
  {
    "setCode": "LOR",
    "nameFR": "",
    "nameEN": "Lost Origin",
    "releaseDate": "09-09-2022"
  },
  {
    "setCode": "PGO",
    "nameFR": "",
    "nameEN": "Pokémon GO",
    "releaseDate": "01-07-2022"
  },
  {
    "setCode": "ASR",
    "nameFR": "",
    "nameEN": "Astral Radiance",
    "releaseDate": "27-05-2022"
  },
  {
    "setCode": "BRS",
    "nameFR": "",
    "nameEN": "Brilliant Stars",
    "releaseDate": "25-02-2022"
  },
  {
    "setCode": "FST",
    "nameFR": "",
    "nameEN": "Fusion Strike",
    "releaseDate": "12-11-2021"
  },
  {
    "setCode": "CEL",
    "nameFR": "",
    "nameEN": "Celebrations",
    "releaseDate": "08-10-2021"
  },
  {
    "setCode": "EVS",
    "nameFR": "",
    "nameEN": "Evolving Skies",
    "releaseDate": "27-08-2021"
  },
  {
    "setCode": "CRE",
    "nameFR": "",
    "nameEN": "Chilling Reign",
    "releaseDate": "18-06-2021"
  },
  {
    "setCode": "BST",
    "nameFR": "",
    "nameEN": "Battle Styles",
    "releaseDate": "19-03-2021"
  },
  {
    "setCode": "SHF",
    "nameFR": "",
    "nameEN": "Shining Fates",
    "releaseDate": "19-02-2021"
  },
  {
    "setCode": "VIV",
    "nameFR": "",
    "nameEN": "Vivid Voltage",
    "releaseDate": "13-11-2020"
  },
  {
    "setCode": "CPA",
    "nameFR": "",
    "nameEN": "Champion's Path",
    "releaseDate": "25-09-2020"
  },
  {
    "setCode": "DAA",
    "nameFR": "",
    "nameEN": "Darkness Ablaze",
    "releaseDate": "14-08-2020"
  },
  {
    "setCode": "RCL",
    "nameFR": "",
    "nameEN": "Rebel Clash",
    "releaseDate": "01-05-2020"
  },
  {
    "setCode": "SSH",
    "nameFR": "",
    "nameEN": "Sword & Shield",
    "releaseDate": "07-02-2020"
  },
  {
    "setCode": "SP",
    "nameFR": "",
    "nameEN": "Sword & Shield Promos",
    "releaseDate": ""
  },
  {
    "setCode": "CEC",
    "nameFR": "",
    "nameEN": "Cosmic Eclipse",
    "releaseDate": "01-11-2019"
  },
  {
    "setCode": "HIF",
    "nameFR": "",
    "nameEN": "Hidden Fates",
    "releaseDate": "23-08-2019"
  },
  {
    "setCode": "UNM",
    "nameFR": "",
    "nameEN": "Unified Minds",
    "releaseDate": "02-08-2019"
  },
  {
    "setCode": "UNB",
    "nameFR": "",
    "nameEN": "Unbroken Bonds",
    "releaseDate": "03-05-2019"
  },
  {
    "setCode": "DET",
    "nameFR": "",
    "nameEN": "Detective Pikachu",
    "releaseDate": "29-03-2019"
  },
  {
    "setCode": "TEU",
    "nameFR": "",
    "nameEN": "Team Up",
    "releaseDate": "01-02-2019"
  },
  {
    "setCode": "LOT",
    "nameFR": "",
    "nameEN": "Lost Thunder",
    "releaseDate": "02-11-2018"
  },
  {
    "setCode": "DRM",
    "nameFR": "",
    "nameEN": "Dragon Majesty",
    "releaseDate": "07-09-2018"
  },
  {
    "setCode": "CES",
    "nameFR": "",
    "nameEN": "Celestial Storm",
    "releaseDate": "03-08-2018"
  },
  {
    "setCode": "FLI",
    "nameFR": "",
    "nameEN": "Forbidden Light",
    "releaseDate": "04-05-2018"
  },
  {
    "setCode": "UPR",
    "nameFR": "",
    "nameEN": "Ultra Prism",
    "releaseDate": "02-02-2018"
  },
  {
    "setCode": "CIN",
    "nameFR": "",
    "nameEN": "Crimson Invasion",
    "releaseDate": "03-11-2017"
  },
  {
    "setCode": "SLG",
    "nameFR": "",
    "nameEN": "Shining Legends",
    "releaseDate": "06-10-2017"
  },
  {
    "setCode": "BUS",
    "nameFR": "",
    "nameEN": "Burning Shadows",
    "releaseDate": "04-08-2017"
  },
  {
    "setCode": "GRI",
    "nameFR": "",
    "nameEN": "Guardians Rising",
    "releaseDate": "05-05-2017"
  },
  {
    "setCode": "SUM",
    "nameFR": "",
    "nameEN": "Sun & Moon",
    "releaseDate": "03-02-2017"
  },
  {
    "setCode": "SMP",
    "nameFR": "",
    "nameEN": "Sun & Moon Promos",
    "releaseDate": ""
  },
  {
    "setCode": "EVO",
    "nameFR": "",
    "nameEN": "Evolutions",
    "releaseDate": "02-11-2016"
  },
  {
    "setCode": "STS",
    "nameFR": "",
    "nameEN": "Steam Siege",
    "releaseDate": "03-08-2016"
  },
  {
    "setCode": "FCO",
    "nameFR": "",
    "nameEN": "Fates Collide",
    "releaseDate": "02-05-2016"
  },
  {
    "setCode": "GEN",
    "nameFR": "",
    "nameEN": "Generations",
    "releaseDate": "22-02-2016"
  },
  {
    "setCode": "BKP",
    "nameFR": "",
    "nameEN": "BREAKpoint",
    "releaseDate": "03-02-2016"
  },
  {
    "setCode": "BKT",
    "nameFR": "",
    "nameEN": "BREAKthrough",
    "releaseDate": "04-11-2015"
  },
  {
    "setCode": "AOR",
    "nameFR": "",
    "nameEN": "Ancient Origins",
    "releaseDate": "12-08-2015"
  },
  {
    "setCode": "ROS",
    "nameFR": "",
    "nameEN": "Roaring Skies",
    "releaseDate": "06-05-2015"
  },
  {
    "setCode": "DCR",
    "nameFR": "",
    "nameEN": "Double Crisis",
    "releaseDate": "25-03-2015"
  },
  {
    "setCode": "PRC",
    "nameFR": "",
    "nameEN": "Primal Clash",
    "releaseDate": "04-02-2015"
  },
  {
    "setCode": "PHF",
    "nameFR": "",
    "nameEN": "Phantom Forces",
    "releaseDate": "05-11-2014"
  },
  {
    "setCode": "FFI",
    "nameFR": "",
    "nameEN": "Furious Fists",
    "releaseDate": "13-08-2014"
  },
  {
    "setCode": "FLF",
    "nameFR": "",
    "nameEN": "Flashfire",
    "releaseDate": "07-05-2014"
  },
  {
    "setCode": "XY",
    "nameFR": "",
    "nameEN": "XY",
    "releaseDate": "05-02-2014"
  },
  {
    "setCode": "KSS",
    "nameFR": "",
    "nameEN": "Kalos Starter Set",
    "releaseDate": "08-11-2013"
  },
  {
    "setCode": "XY-P",
    "nameFR": "",
    "nameEN": "XY Promos",
    "releaseDate": ""
  },
  {
    "setCode": "LTR",
    "nameFR": "",
    "nameEN": "Legendary Treasures",
    "releaseDate": "06-11-2013"
  },
  {
    "setCode": "PLB",
    "nameFR": "",
    "nameEN": "Plasma Blast",
    "releaseDate": "14-08-2013"
  },
  {
    "setCode": "PLF",
    "nameFR": "",
    "nameEN": "Plasma Freeze",
    "releaseDate": "08-05-2013"
  },
  {
    "setCode": "PLS",
    "nameFR": "",
    "nameEN": "Plasma Storm",
    "releaseDate": "06-02-2013"
  },
  {
    "setCode": "BCR",
    "nameFR": "",
    "nameEN": "Boundaries Crossed",
    "releaseDate": "07-11-2012"
  },
  {
    "setCode": "DRV",
    "nameFR": "",
    "nameEN": "Dragon Vault",
    "releaseDate": "05-10-2012"
  },
  {
    "setCode": "DRX",
    "nameFR": "",
    "nameEN": "Dragons Exalted",
    "releaseDate": "15-08-2012"
  },
  {
    "setCode": "DEX",
    "nameFR": "",
    "nameEN": "Dark Explorers",
    "releaseDate": "09-05-2012"
  },
  {
    "setCode": "NXD",
    "nameFR": "",
    "nameEN": "Next Destinies",
    "releaseDate": "08-02-2012"
  },
  {
    "setCode": "NVI",
    "nameFR": "",
    "nameEN": "Noble Victories",
    "releaseDate": "16-11-2011"
  },
  {
    "setCode": "EPO",
    "nameFR": "",
    "nameEN": "Emerging Powers",
    "releaseDate": "31-08-2011"
  },
  {
    "setCode": "BLW",
    "nameFR": "",
    "nameEN": "Black & White",
    "releaseDate": "25-04-2011"
  },
  {
    "setCode": "BWP",
    "nameFR": "",
    "nameEN": "Black & White Promos",
    "releaseDate": ""
  },
  {
    "setCode": "CL",
    "nameFR": "",
    "nameEN": "Call of Legends",
    "releaseDate": "09-02-2011"
  },
  {
    "setCode": "TM",
    "nameFR": "",
    "nameEN": "Triumphant",
    "releaseDate": "03-11-2010"
  },
  {
    "setCode": "UD",
    "nameFR": "",
    "nameEN": "Undaunted",
    "releaseDate": "18-08-2010"
  },
  {
    "setCode": "UL",
    "nameFR": "",
    "nameEN": "Unleashed",
    "releaseDate": "12-05-2010"
  },
  {
    "setCode": "HS",
    "nameFR": "",
    "nameEN": "HeartGold & SoulSilver",
    "releaseDate": "10-02-2010"
  },
  {
    "setCode": "HSP",
    "nameFR": "",
    "nameEN": "HeartGold & SoulSilver Promos",
    "releaseDate": ""
  },
  {
    "setCode": "RM",
    "nameFR": "",
    "nameEN": "Pokémon Rumble",
    "releaseDate": "02-12-2009"
  },
  {
    "setCode": "AR",
    "nameFR": "",
    "nameEN": "Arceus",
    "releaseDate": "04-11-2009"
  },
  {
    "setCode": "SV",
    "nameFR": "",
    "nameEN": "Supreme Victors",
    "releaseDate": "19-08-2009"
  },
  {
    "setCode": "RR",
    "nameFR": "",
    "nameEN": "Rising Rivals",
    "releaseDate": "20-05-2009"
  },
  {
    "setCode": "P9",
    "nameFR": "",
    "nameEN": "POP Series 9",
    "releaseDate": "01-03-2009"
  },
  {
    "setCode": "PL",
    "nameFR": "",
    "nameEN": "Platinum",
    "releaseDate": "11-02-2009"
  },
  {
    "setCode": "STF",
    "nameFR": "",
    "nameEN": "Stormfront",
    "releaseDate": "05-11-2008"
  },
  {
    "setCode": "P8",
    "nameFR": "",
    "nameEN": "POP Series 8",
    "releaseDate": "01-09-2008"
  },
  {
    "setCode": "LA",
    "nameFR": "",
    "nameEN": "Legends Awakened",
    "releaseDate": "20-08-2008"
  },
  {
    "setCode": "MD",
    "nameFR": "",
    "nameEN": "Majestic Dawn",
    "releaseDate": "21-05-2008"
  },
  {
    "setCode": "POP7",
    "nameFR": "",
    "nameEN": "POP Series 7",
    "releaseDate": "01-03-2008"
  },
  {
    "setCode": "GE",
    "nameFR": "",
    "nameEN": "Great Encounters",
    "releaseDate": "13-02-2008"
  },
  {
    "setCode": "SW",
    "nameFR": "",
    "nameEN": "Secret Wonders",
    "releaseDate": "07-11-2007"
  },
  {
    "setCode": "P6",
    "nameFR": "",
    "nameEN": "POP Series 6",
    "releaseDate": "01-09-2007"
  },
  {
    "setCode": "MT",
    "nameFR": "",
    "nameEN": "Mysterious Treasures",
    "releaseDate": "22-08-2007"
  },
  {
    "setCode": "DP",
    "nameFR": "",
    "nameEN": "Diamond & Pearl",
    "releaseDate": "23-05-2007"
  },
  {
    "setCode": "DPP",
    "nameFR": "",
    "nameEN": "Diamond & Pearl Promos",
    "releaseDate": ""
  },
  {
    "setCode": "P5",
    "nameFR": "",
    "nameEN": "POP Series 5",
    "releaseDate": "01-03-2007"
  },
  {
    "setCode": "PK",
    "nameFR": "",
    "nameEN": "Power Keepers",
    "releaseDate": "14-02-2007"
  },
  {
    "setCode": "DF",
    "nameFR": "",
    "nameEN": "Dragon Frontiers",
    "releaseDate": "08-11-2006"
  },
  {
    "setCode": "CG",
    "nameFR": "",
    "nameEN": "Crystal Guardians",
    "releaseDate": "30-08-2006"
  },
  {
    "setCode": "P4",
    "nameFR": "",
    "nameEN": "POP Series 4",
    "releaseDate": "01-08-2006"
  },
  {
    "setCode": "HP",
    "nameFR": "",
    "nameEN": "Holon Phantoms",
    "releaseDate": "03-05-2006"
  },
  {
    "setCode": "P3",
    "nameFR": "",
    "nameEN": "POP Series 3",
    "releaseDate": "01-04-2006"
  },
  {
    "setCode": "LM",
    "nameFR": "",
    "nameEN": "Legend Maker",
    "releaseDate": "13-02-2006"
  },
  {
    "setCode": "DS",
    "nameFR": "",
    "nameEN": "Delta Species",
    "releaseDate": "31-10-2005"
  },
  {
    "setCode": "UF",
    "nameFR": "",
    "nameEN": "Unseen Forces",
    "releaseDate": "22-08-2005"
  },
  {
    "setCode": "P2",
    "nameFR": "",
    "nameEN": "POP Series 2",
    "releaseDate": "01-08-2005"
  },
  {
    "setCode": "EM",
    "nameFR": "",
    "nameEN": "Emerald",
    "releaseDate": "09-05-2005"
  },
  {
    "setCode": "DX",
    "nameFR": "",
    "nameEN": "Deoxys",
    "releaseDate": "14-02-2005"
  },
  {
    "setCode": "TRR",
    "nameFR": "",
    "nameEN": "Team Rocket Returns",
    "releaseDate": "08-11-2004"
  },
  {
    "setCode": "POP1",
    "nameFR": "",
    "nameEN": "POP Series 1",
    "releaseDate": "01-09-2004"
  },
  {
    "setCode": "RG",
    "nameFR": "",
    "nameEN": "FireRed & LeafGreen",
    "releaseDate": "30-08-2004"
  },
  {
    "setCode": "HL",
    "nameFR": "",
    "nameEN": "Hidden Legends",
    "releaseDate": "14-06-2004"
  },
  {
    "setCode": "MA",
    "nameFR": "",
    "nameEN": "Team Magma vs Team Aqua",
    "releaseDate": "15-03-2004"
  },
  {
    "setCode": "DR",
    "nameFR": "",
    "nameEN": "Dragon",
    "releaseDate": "24-11-2003"
  },
  {
    "setCode": "SS",
    "nameFR": "",
    "nameEN": "Sandstorm",
    "releaseDate": "18-09-2003"
  },
  {
    "setCode": "RS",
    "nameFR": "",
    "nameEN": "Ruby & Sapphire",
    "releaseDate": "18-06-2003"
  },
  {
    "setCode": "NP",
    "nameFR": "",
    "nameEN": "Nintendo Promos",
    "releaseDate": ""
  },
  {
    "setCode": "E3",
    "nameFR": "",
    "nameEN": "Skyridge",
    "releaseDate": "12-05-2003"
  },
  {
    "setCode": "AQ",
    "nameFR": "",
    "nameEN": "Aquapolis",
    "releaseDate": "15-01-2003"
  },
  {
    "setCode": "BG",
    "nameFR": "",
    "nameEN": "Best of Game",
    "releaseDate": "01-12-2002"
  },
  {
    "setCode": "E1",
    "nameFR": "",
    "nameEN": "Expedition",
    "releaseDate": "15-09-2002"
  },
  {
    "setCode": "LC",
    "nameFR": "",
    "nameEN": "Legendary Collection",
    "releaseDate": "24-05-2002"
  },
  {
    "setCode": "NDE",
    "nameFR": "",
    "nameEN": "Neo Destiny",
    "releaseDate": "28-02-2002"
  },
  {
    "setCode": "NR",
    "nameFR": "",
    "nameEN": "Neo Revelation",
    "releaseDate": "21-09-2001"
  },
  {
    "setCode": "SI",
    "nameFR": "",
    "nameEN": "Southern Islands",
    "releaseDate": "31-07-2001"
  },
  {
    "setCode": "NDI",
    "nameFR": "",
    "nameEN": "Neo Discovery",
    "releaseDate": "01-06-2001"
  },
  {
    "setCode": "NG",
    "nameFR": "",
    "nameEN": "Neo Genesis",
    "releaseDate": "16-12-2000"
  },
  {
    "setCode": "G2",
    "nameFR": "",
    "nameEN": "Gym Challenge",
    "releaseDate": "16-10-2000"
  },
  {
    "setCode": "GH",
    "nameFR": "",
    "nameEN": "Gym Heroes",
    "releaseDate": "14-08-2000"
  },
  {
    "setCode": "TR",
    "nameFR": "",
    "nameEN": "Team Rocket",
    "releaseDate": "24-04-2000"
  },
  {
    "setCode": "BS2",
    "nameFR": "",
    "nameEN": "Base Set 2",
    "releaseDate": "24-02-2000"
  },
  {
    "setCode": "FO",
    "nameFR": "",
    "nameEN": "Fossil",
    "releaseDate": "10-10-1999"
  },
  {
    "setCode": "JU",
    "nameFR": "",
    "nameEN": "Jungle",
    "releaseDate": "16-06-1999"
  },
  {
    "setCode": "BS",
    "nameFR": "",
    "nameEN": "Base Set",
    "releaseDate": "09-01-1999"
  },
  {
    "setCode": "WP",
    "nameFR": "",
    "nameEN": "WotC Promos",
    "releaseDate": ""
  }
]